sqlalchemy_pretty_sql.py
sqlalchemy_pretty_sql-0.4.0.dist-info/LICENSE
sqlalchemy_pretty_sql-0.4.0.dist-info/METADATA
sqlalchemy_pretty_sql-0.4.0.dist-info/WHEEL
sqlalchemy_pretty_sql-0.4.0.dist-info/top_level.txt
sqlalchemy_pretty_sql-0.4.0.dist-info/RECORD
